{
  "full_name": "django/django",
  "html_url": "https://github.com/django/django",
  "start_date": "2024-06-03T01:14:49Z",
  "end_date": "2025-07-03T01:14:49Z",
  "months": 13,
  "forks_count": 32701,
  "cumulative_total_committers": 3117,
  "new_committers_per_month": 12,
  "total_active_committers_per_month": 33,
  "new_committers_percentage": 36,
  "commits_per_month": 76,
  "commits_per_committer_per_month": 2.30,
  "has_issues": false,
  "PRs_merged_or_closed_percentage": 86,
  "PRs_merged_vs_commits_ratio": 80,
  "PRs_merged_per_month": 61,
  "PRs_closed_per_month": 32,
  "PRs_opened_per_month": 107,
  "PRs_increase_decrease": 13,
  "PRs_open_age_days_stats": {
    "records": 346,
    "newest": 0,
    "percentile_25": 73,
    "median": 215,
    "mean": 325,
    "percentile_75": 469,
    "percentile_90": 783,
    "oldest": 2246,
    "std_dev": 350
  },
  "PRs_time_to_resolve_days_stats": {
    "records": 1000,
    "fastest": 0,
    "percentile_25": 0,
    "median": 2,
    "mean": 34,
    "percentile_75": 14,
    "percentile_90": 83,
    "longest": 2581,
    "std_dev": 130
  },
  "PRs_open_count": 346,
  "PRs_resolved_count": 19136,
  "PRs_resolved_to_open_ratio": 55.31,
  "PRs_open_to_monthly_ratio": 3.23
}
