{
  "full_name": "elixir-lang/elixir",
  "html_url": "https://github.com/elixir-lang/elixir",
  "start_date": "2023-02-22T09:12:21Z",
  "end_date": "2024-03-22T09:12:21Z",
  "months": 13,
  "forks_count": 3248,
  "cumulative_total_committers": 1430,
  "new_committers_per_month": 8,
  "total_active_committers_per_month": 20,
  "new_committers_percentage": 40,
  "commits_per_month": 81,
  "commits_per_committer_per_month": 4.05,
  "has_issues": true,
  "issues_closed_percentage": 100,
  "issues_closed_per_month": 28,
  "issues_opened_per_month": 28,
  "issues_increase_decrease": 0,
  "issues_open_age_days_stats": {
    "records": 16,
    "newest": 0,
    "percentile_25": 59,
    "median": 284,
    "mean": 609,
    "percentile_75": 1013,
    "percentile_90": 1595,
    "oldest": 2044,
    "std_dev": 713
  },
  "issues_time_to_resolve_days_stats": {
    "records": 1000,
    "fastest": 0,
    "percentile_25": 0,
    "median": 0,
    "mean": 19,
    "percentile_75": 1,
    "percentile_90": 22,
    "longest": 1673,
    "std_dev": 119
  },
  "issues_open_count": 16,
  "issues_resolved_count": 5255,
  "issues_resolved_to_open_ratio": 328.44,
  "issues_resolved_to_commits_percentage": 26,
  "issues_open_to_monthly_ratio": 0.57,
  "PRs_merged_or_closed_percentage": 100,
  "PRs_merged_vs_commits_ratio": 50,
  "PRs_merged_per_month": 41,
  "PRs_closed_per_month": 7,
  "PRs_opened_per_month": 48,
  "PRs_increase_decrease": 0,
  "PRs_open_age_days_stats": {
    "records": 8,
    "newest": 0,
    "percentile_25": 3,
    "median": 15,
    "mean": 46,
    "percentile_75": 61,
    "percentile_90": 102,
    "oldest": 212,
    "std_dev": 75
  },
  "PRs_time_to_resolve_days_stats": {
    "records": 1000,
    "fastest": 0,
    "percentile_25": 0,
    "median": 0,
    "mean": 2,
    "percentile_75": 0,
    "percentile_90": 2,
    "longest": 567,
    "std_dev": 22
  },
  "PRs_open_count": 8,
  "PRs_resolved_count": 8101,
  "PRs_resolved_to_open_ratio": 1012.62,
  "PRs_open_to_monthly_ratio": 0.17
}
