{
  "full_name": "Homebrew/homebrew-core",
  "html_url": "https://github.com/Homebrew/homebrew-core",
  "start_date": "2021-07-25T11:19:08Z",
  "end_date": "2022-08-25T11:19:08Z",
  "months": 13,
  "forks_count": 10732,
  "cumulative_total_committers": 11524,
  "new_committers_per_month": 58,
  "total_active_committers_per_month": 231,
  "new_committers_percentage": 25,
  "commits_per_month": 18768,
  "commits_per_committer_per_month": 81.25,
  "has_issues": true,
  "issues_closed_percentage": 100,
  "issues_closed_per_month": 32,
  "issues_opened_per_month": 32,
  "issues_increase_decrease": 0,
  "issues_open_age_days_stats": {
    "records": 21,
    "newest": 0,
    "percentile_25": 26,
    "median": 80,
    "mean": 203,
    "percentile_75": 307,
    "percentile_90": 478,
    "oldest": 990,
    "std_dev": 266
  },
  "issues_time_to_resolve_days_stats": {
    "records": 1000,
    "fastest": 0,
    "percentile_25": 0,
    "median": 0,
    "mean": 15,
    "percentile_75": 8,
    "percentile_90": 33,
    "longest": 1731,
    "std_dev": 70
  },
  "issues_open_count": 21,
  "issues_resolved_count": 4757,
  "issues_resolved_to_open_ratio": 226.52,
  "issues_resolved_to_commits_percentage": 1,
  "issues_open_to_monthly_ratio": 0.66,
  "PRs_merged_or_closed_percentage": 99,
  "PRs_merged_vs_commits_ratio": 0,
  "PRs_merged_per_month": 121,
  "PRs_closed_per_month": 1915,
  "PRs_opened_per_month": 2040,
  "PRs_increase_decrease": 3,
  "PRs_open_age_days_stats": {
    "records": 150,
    "newest": 0,
    "percentile_25": 3,
    "median": 14,
    "mean": 22,
    "percentile_75": 21,
    "percentile_90": 38,
    "oldest": 336,
    "std_dev": 38
  },
  "PRs_time_to_resolve_days_stats": {
    "records": 1000,
    "fastest": 0,
    "percentile_25": 0,
    "median": 0,
    "mean": 2,
    "percentile_75": 0,
    "percentile_90": 2,
    "longest": 166,
    "std_dev": 9
  },
  "PRs_open_count": 150,
  "PRs_resolved_count": 103637,
  "PRs_resolved_to_open_ratio": 690.91,
  "PRs_open_to_monthly_ratio": 0.07
}
