{
  "full_name": "home-assistant/home-assistant.io",
  "html_url": "https://github.com/home-assistant/home-assistant.io",
  "start_date": "2023-04-26T10:15:01Z",
  "end_date": "2024-05-26T10:15:01Z",
  "months": 13,
  "forks_count": 7029,
  "cumulative_total_committers": 5025,
  "new_committers_per_month": 33,
  "total_active_committers_per_month": 93,
  "new_committers_percentage": 35,
  "commits_per_month": 267,
  "commits_per_committer_per_month": 2.87,
  "has_issues": true,
  "issues_closed_percentage": 85,
  "issues_closed_per_month": 128,
  "issues_opened_per_month": 150,
  "issues_increase_decrease": 22,
  "issues_open_age_days_stats": {
    "records": 459,
    "newest": 0,
    "percentile_25": 46,
    "median": 98,
    "mean": 144,
    "percentile_75": 203,
    "percentile_90": 235,
    "oldest": 1770,
    "std_dev": 178
  },
  "issues_time_to_resolve_days_stats": {
    "records": 1000,
    "fastest": 0,
    "percentile_25": 0,
    "median": 1,
    "mean": 25,
    "percentile_75": 60,
    "percentile_90": 72,
    "longest": 350,
    "std_dev": 44
  },
  "issues_open_count": 459,
  "issues_resolved_count": 6393,
  "issues_resolved_to_open_ratio": 13.93,
  "issues_resolved_to_commits_percentage": 20,
  "issues_open_to_monthly_ratio": 3.06,
  "PRs_merged_or_closed_percentage": 101,
  "PRs_merged_vs_commits_ratio": 89,
  "PRs_merged_per_month": 239,
  "PRs_closed_per_month": 57,
  "PRs_opened_per_month": 291,
  "PRs_increase_decrease": -4,
  "PRs_open_age_days_stats": {
    "records": 173,
    "newest": 0,
    "percentile_25": 19,
    "median": 48,
    "mean": 88,
    "percentile_75": 98,
    "percentile_90": 179,
    "oldest": 876,
    "std_dev": 133
  },
  "PRs_time_to_resolve_days_stats": {
    "records": 1000,
    "fastest": 0,
    "percentile_25": 0,
    "median": 0,
    "mean": 22,
    "percentile_75": 3,
    "percentile_90": 44,
    "longest": 924,
    "std_dev": 82
  },
  "PRs_open_count": 173,
  "PRs_resolved_count": 25700,
  "PRs_resolved_to_open_ratio": 148.55,
  "PRs_open_to_monthly_ratio": 0.59
}
