{
  "full_name": "kubernetes/website",
  "html_url": "https://github.com/kubernetes/website",
  "start_date": "2023-04-30T05:05:05Z",
  "end_date": "2024-05-31T05:05:05Z",
  "months": 13,
  "forks_count": 13981,
  "cumulative_total_committers": 5641,
  "new_committers_per_month": 40,
  "total_active_committers_per_month": 107,
  "new_committers_percentage": 37,
  "commits_per_month": 394,
  "commits_per_committer_per_month": 3.68,
  "has_issues": true,
  "issues_closed_percentage": 100,
  "issues_closed_per_month": 105,
  "issues_opened_per_month": 104,
  "issues_increase_decrease": -1,
  "issues_open_age_days_stats": {
    "records": 606,
    "newest": 0,
    "percentile_25": 65,
    "median": 239,
    "mean": 394,
    "percentile_75": 556,
    "percentile_90": 922,
    "oldest": 2943,
    "std_dev": 472
  },
  "issues_time_to_resolve_days_stats": {
    "records": 1000,
    "fastest": 0,
    "percentile_25": 2,
    "median": 38,
    "mean": 143,
    "percentile_75": 213,
    "percentile_90": 359,
    "longest": 2509,
    "std_dev": 262
  },
  "issues_open_count": 606,
  "issues_resolved_count": 11445,
  "issues_resolved_to_open_ratio": 18.89,
  "issues_resolved_to_commits_percentage": 23,
  "issues_open_to_monthly_ratio": 5.83,
  "PRs_merged_or_closed_percentage": 102,
  "PRs_merged_vs_commits_ratio": 67,
  "PRs_merged_per_month": 265,
  "PRs_closed_per_month": 69,
  "PRs_opened_per_month": 327,
  "PRs_increase_decrease": -7,
  "PRs_open_age_days_stats": {
    "records": 241,
    "newest": 0,
    "percentile_25": 15,
    "median": 28,
    "mean": 71,
    "percentile_75": 104,
    "percentile_90": 175,
    "oldest": 763,
    "std_dev": 95
  },
  "PRs_time_to_resolve_days_stats": {
    "records": 1000,
    "fastest": 0,
    "percentile_25": 0,
    "median": 2,
    "mean": 25,
    "percentile_75": 21,
    "percentile_90": 71,
    "longest": 617,
    "std_dev": 59
  },
  "PRs_open_count": 241,
  "PRs_resolved_count": 33903,
  "PRs_resolved_to_open_ratio": 140.68,
  "PRs_open_to_monthly_ratio": 0.74
}
