{
  "full_name": "mdn/content",
  "html_url": "https://github.com/mdn/content",
  "start_date": "2023-02-22T08:27:05Z",
  "end_date": "2024-03-22T08:27:05Z",
  "months": 13,
  "forks_count": 22398,
  "cumulative_total_committers": 4239,
  "new_committers_per_month": 81,
  "total_active_committers_per_month": 145,
  "new_committers_percentage": 55,
  "commits_per_month": 403,
  "commits_per_committer_per_month": 2.78,
  "has_issues": true,
  "issues_closed_percentage": 94,
  "issues_closed_per_month": 122,
  "issues_opened_per_month": 129,
  "issues_increase_decrease": 6,
  "issues_open_age_days_stats": {
    "records": 718,
    "newest": 0,
    "percentile_25": 126,
    "median": 357,
    "mean": 418,
    "percentile_75": 675,
    "percentile_90": 951,
    "oldest": 1183,
    "std_dev": 331
  },
  "issues_time_to_resolve_days_stats": {
    "records": 1000,
    "fastest": 0,
    "percentile_25": 0,
    "median": 7,
    "mean": 72,
    "percentile_75": 34,
    "percentile_90": 279,
    "longest": 884,
    "std_dev": 164
  },
  "issues_open_count": 718,
  "issues_resolved_count": 6828,
  "issues_resolved_to_open_ratio": 9.51,
  "issues_resolved_to_commits_percentage": 31,
  "issues_open_to_monthly_ratio": 5.57,
  "PRs_merged_or_closed_percentage": 99,
  "PRs_merged_vs_commits_ratio": 99,
  "PRs_merged_per_month": 402,
  "PRs_closed_per_month": 54,
  "PRs_opened_per_month": 457,
  "PRs_increase_decrease": 0,
  "PRs_open_age_days_stats": {
    "records": 113,
    "newest": 0,
    "percentile_25": 18,
    "median": 44,
    "mean": 64,
    "percentile_75": 101,
    "percentile_90": 128,
    "oldest": 377,
    "std_dev": 63
  },
  "PRs_time_to_resolve_days_stats": {
    "records": 1000,
    "fastest": 0,
    "percentile_25": 0,
    "median": 0,
    "mean": 7,
    "percentile_75": 4,
    "percentile_90": 18,
    "longest": 204,
    "std_dev": 21
  },
  "PRs_open_count": 113,
  "PRs_resolved_count": 23286,
  "PRs_resolved_to_open_ratio": 206.07,
  "PRs_open_to_monthly_ratio": 0.25
}
