{
  "full_name": "MicrosoftDocs/azure-devops-docs",
  "html_url": "https://github.com/MicrosoftDocs/azure-devops-docs",
  "start_date": "2021-06-09T15:02:56Z",
  "end_date": "2022-07-09T15:02:56Z",
  "months": 13,
  "forks_count": 2131,
  "cumulative_total_committers": 1330,
  "new_committers_per_month": 16,
  "total_active_committers_per_month": 45,
  "new_committers_percentage": 35,
  "commits_per_month": 327,
  "commits_per_committer_per_month": 7.27,
  "has_issues": true,
  "issues_closed_percentage": 74,
  "issues_closed_per_month": 71,
  "issues_opened_per_month": 95,
  "issues_increase_decrease": 23,
  "issues_open_age_days_stats": {
    "records": 1000,
    "newest": 0,
    "percentile_25": 202,
    "median": 380,
    "mean": 431,
    "percentile_75": 586,
    "percentile_90": 892,
    "oldest": 1530,
    "std_dev": 315
  },
  "issues_time_to_resolve_days_stats": {
    "records": 1000,
    "fastest": 0,
    "percentile_25": 0,
    "median": 13,
    "mean": 77,
    "percentile_75": 80,
    "percentile_90": 269,
    "longest": 1107,
    "std_dev": 143
  },
  "issues_open_count": 1133,
  "issues_resolved_count": 8584,
  "issues_resolved_to_open_ratio": 7.58,
  "issues_open_to_monthly_ratio": 11.93,
  "PRs_merged_or_closed_percentage": 91,
  "PRs_merged_vs_commits_ratio": 5,
  "PRs_merged_per_month": 19,
  "PRs_closed_per_month": 2,
  "PRs_opened_per_month": 23,
  "PRs_increase_decrease": 0,
  "PRs_open_age_days_stats": {
    "records": 21,
    "newest": 3,
    "percentile_25": 16,
    "median": 35,
    "mean": 106,
    "percentile_75": 177,
    "percentile_90": 249,
    "oldest": 339,
    "std_dev": 116
  },
  "PRs_time_to_resolve_days_stats": {
    "records": 1000,
    "fastest": 0,
    "percentile_25": 0,
    "median": 1,
    "mean": 22,
    "percentile_75": 14,
    "percentile_90": 73,
    "longest": 506,
    "std_dev": 52
  },
  "PRs_open_count": 21,
  "PRs_resolved_count": 2559,
  "PRs_resolved_to_open_ratio": 121.86,
  "PRs_open_to_monthly_ratio": 0.91
}
