{
  "full_name": "moby/moby",
  "html_url": "https://github.com/moby/moby",
  "start_date": "2023-04-30T05:26:15Z",
  "end_date": "2024-05-31T05:26:15Z",
  "months": 13,
  "forks_count": 18564,
  "cumulative_total_committers": 2438,
  "new_committers_per_month": 4,
  "total_active_committers_per_month": 14,
  "new_committers_percentage": 28,
  "commits_per_month": 156,
  "commits_per_committer_per_month": 11.14,
  "has_issues": true,
  "issues_closed_percentage": 245,
  "issues_closed_per_month": 118,
  "issues_opened_per_month": 48,
  "issues_increase_decrease": -69,
  "issues_open_age_days_stats": {
    "records": 1000,
    "newest": 0,
    "percentile_25": 231,
    "median": 1372,
    "mean": 1477,
    "percentile_75": 2648,
    "percentile_90": 2976,
    "oldest": 3965,
    "std_dev": 1187
  },
  "issues_time_to_resolve_days_stats": {
    "records": 1000,
    "fastest": 0,
    "percentile_25": 9,
    "median": 1258,
    "mean": 1224,
    "percentile_75": 2319,
    "percentile_90": 2561,
    "longest": 3579,
    "std_dev": 1106
  },
  "issues_open_count": 3013,
  "issues_resolved_count": 19487,
  "issues_resolved_to_open_ratio": 6.47,
  "issues_resolved_to_commits_percentage": 39,
  "issues_open_to_monthly_ratio": 62.77,
  "PRs_merged_or_closed_percentage": 95,
  "PRs_merged_vs_commits_ratio": 69,
  "PRs_merged_per_month": 108,
  "PRs_closed_per_month": 10,
  "PRs_opened_per_month": 123,
  "PRs_increase_decrease": 4,
  "PRs_open_age_days_stats": {
    "records": 385,
    "newest": 0,
    "percentile_25": 164,
    "median": 401,
    "mean": 642,
    "percentile_75": 1093,
    "percentile_90": 1535,
    "oldest": 2490,
    "std_dev": 580
  },
  "PRs_time_to_resolve_days_stats": {
    "records": 1000,
    "fastest": 0,
    "percentile_25": 0,
    "median": 0,
    "mean": 39,
    "percentile_75": 6,
    "percentile_90": 40,
    "longest": 2265,
    "std_dev": 185
  },
  "PRs_open_count": 385,
  "PRs_resolved_count": 24319,
  "PRs_resolved_to_open_ratio": 63.17,
  "PRs_open_to_monthly_ratio": 3.13
}
