{
  "full_name": "vuejs/docs",
  "html_url": "https://github.com/vuejs/docs",
  "start_date": "2023-04-15T08:48:56Z",
  "end_date": "2024-05-15T08:48:56Z",
  "months": 13,
  "forks_count": 4101,
  "cumulative_total_committers": 558,
  "new_committers_per_month": 11,
  "total_active_committers_per_month": 18,
  "new_committers_percentage": 61,
  "commits_per_month": 30,
  "commits_per_committer_per_month": 1.67,
  "has_issues": true,
  "issues_closed_percentage": 90,
  "issues_closed_per_month": 10,
  "issues_opened_per_month": 11,
  "issues_increase_decrease": 1,
  "issues_open_age_days_stats": {
    "records": 107,
    "newest": 0,
    "percentile_25": 300,
    "median": 570,
    "mean": 582,
    "percentile_75": 853,
    "percentile_90": 1086,
    "oldest": 1393,
    "std_dev": 352
  },
  "issues_time_to_resolve_days_stats": {
    "records": 793,
    "fastest": 0,
    "percentile_25": 0,
    "median": 3,
    "mean": 51,
    "percentile_75": 34,
    "percentile_90": 176,
    "longest": 989,
    "std_dev": 113
  },
  "issues_open_count": 107,
  "issues_resolved_count": 793,
  "issues_resolved_to_open_ratio": 7.41,
  "issues_resolved_to_commits_percentage": 36,
  "issues_open_to_monthly_ratio": 9.73,
  "PRs_merged_or_closed_percentage": 100,
  "PRs_merged_vs_commits_ratio": 73,
  "PRs_merged_per_month": 22,
  "PRs_closed_per_month": 6,
  "PRs_opened_per_month": 28,
  "PRs_increase_decrease": 0,
  "PRs_open_age_days_stats": {
    "records": 28,
    "newest": 0,
    "percentile_25": 4,
    "median": 35,
    "mean": 104,
    "percentile_75": 178,
    "percentile_90": 313,
    "oldest": 402,
    "std_dev": 126
  },
  "PRs_time_to_resolve_days_stats": {
    "records": 1000,
    "fastest": 0,
    "percentile_25": 0,
    "median": 0,
    "mean": 12,
    "percentile_75": 5,
    "percentile_90": 21,
    "longest": 531,
    "std_dev": 43
  },
  "PRs_open_count": 28,
  "PRs_resolved_count": 1848,
  "PRs_resolved_to_open_ratio": 66.00,
  "PRs_open_to_monthly_ratio": 1.00
}
