{
  "full_name": "vuejs/docs",
  "html_url": "https://github.com/vuejs/docs",
  "start_date": "2022-01-10T13:20:50Z",
  "end_date": "2023-02-10T13:20:50Z",
  "months": 13,
  "forks_count": 2739,
  "cumulative_total_committers": 393,
  "new_committers_per_month": 14,
  "total_active_committers_per_month": 21,
  "new_committers_percentage": 66,
  "commits_per_month": 133,
  "commits_per_committer_per_month": 6.33,
  "has_issues": true,
  "issues_closed_percentage": 107,
  "issues_closed_per_month": 15,
  "issues_opened_per_month": 14,
  "issues_increase_decrease": 0,
  "issues_open_age_days_stats": {
    "records": 76,
    "newest": 0,
    "percentile_25": 113,
    "median": 264,
    "mean": 331,
    "percentile_75": 504,
    "percentile_90": 685,
    "oldest": 936,
    "std_dev": 263
  },
  "issues_time_to_resolve_days_stats": {
    "records": 645,
    "fastest": 0,
    "percentile_25": 0,
    "median": 3,
    "mean": 52,
    "percentile_75": 37,
    "percentile_90": 189,
    "longest": 770,
    "std_dev": 112
  },
  "issues_open_count": 76,
  "issues_resolved_count": 645,
  "issues_resolved_to_open_ratio": 8.49,
  "issues_resolved_to_commits_percentage": 37,
  "issues_open_to_monthly_ratio": 5.43,
  "PRs_merged_or_closed_percentage": 97,
  "PRs_merged_vs_commits_ratio": 21,
  "PRs_merged_per_month": 28,
  "PRs_closed_per_month": 14,
  "PRs_opened_per_month": 43,
  "PRs_increase_decrease": 0,
  "PRs_open_age_days_stats": {
    "records": 17,
    "newest": 2,
    "percentile_25": 8,
    "median": 26,
    "mean": 94,
    "percentile_75": 168,
    "percentile_90": 218,
    "oldest": 385,
    "std_dev": 112
  },
  "PRs_time_to_resolve_days_stats": {
    "records": 1000,
    "fastest": 0,
    "percentile_25": 0,
    "median": 0,
    "mean": 6,
    "percentile_75": 3,
    "percentile_90": 11,
    "longest": 451,
    "std_dev": 26
  },
  "PRs_open_count": 17,
  "PRs_resolved_count": 1426,
  "PRs_resolved_to_open_ratio": 83.88,
  "PRs_open_to_monthly_ratio": 0.40
}
