{
  "full_name": "w3c/csswg-drafts",
  "html_url": "https://github.com/w3c/csswg-drafts",
  "start_date": "2023-04-15T03:32:42Z",
  "end_date": "2024-05-15T03:32:42Z",
  "months": 13,
  "forks_count": 631,
  "cumulative_total_committers": 420,
  "new_committers_per_month": 2,
  "total_active_committers_per_month": 17,
  "new_committers_percentage": 11,
  "commits_per_month": 97,
  "commits_per_committer_per_month": 5.71,
  "has_issues": true,
  "issues_closed_percentage": 62,
  "issues_closed_per_month": 56,
  "issues_opened_per_month": 89,
  "issues_increase_decrease": 33,
  "issues_open_age_days_stats": {
    "records": 1000,
    "newest": 0,
    "percentile_25": 90,
    "median": 237,
    "mean": 563,
    "percentile_75": 729,
    "percentile_90": 1826,
    "oldest": 3120,
    "std_dev": 707
  },
  "issues_time_to_resolve_days_stats": {
    "records": 1000,
    "fastest": 0,
    "percentile_25": 2,
    "median": 68,
    "mean": 299,
    "percentile_75": 265,
    "percentile_90": 988,
    "longest": 2822,
    "std_dev": 553
  },
  "issues_open_count": 3134,
  "issues_resolved_count": 5065,
  "issues_resolved_to_open_ratio": 1.62,
  "issues_resolved_to_commits_percentage": 16,
  "issues_open_to_monthly_ratio": 35.21,
  "PRs_merged_or_closed_percentage": 89,
  "PRs_merged_vs_commits_ratio": 24,
  "PRs_merged_per_month": 24,
  "PRs_closed_per_month": 2,
  "PRs_opened_per_month": 29,
  "PRs_increase_decrease": 1,
  "PRs_open_age_days_stats": {
    "records": 76,
    "newest": 1,
    "percentile_25": 107,
    "median": 235,
    "mean": 585,
    "percentile_75": 948,
    "percentile_90": 1665,
    "oldest": 2632,
    "std_dev": 678
  },
  "PRs_time_to_resolve_days_stats": {
    "records": 1000,
    "fastest": 0,
    "percentile_25": 0,
    "median": 1,
    "mean": 40,
    "percentile_75": 12,
    "percentile_90": 81,
    "longest": 1684,
    "std_dev": 145
  },
  "PRs_open_count": 76,
  "PRs_resolved_count": 1908,
  "PRs_resolved_to_open_ratio": 25.11,
  "PRs_open_to_monthly_ratio": 2.62
}
